Metadata-Version: 2.1
Name: nonebot-plugin-quickban
Version: 0.0.1
Summary: 快捷禁言
Home-page: https://github.com/mas-alone/nonebot-plugin-sleep
Author: ghb010417
Author-email: 113217194@qq.com
Classifier: Programming Language :: Python :: 3.8
Classifier: License :: OSI Approved :: GNU Affero General Public License v3
Classifier: Operating System :: OS Independent
License-File: LICENSE
Requires-Dist: nonebot2 >=2.0.0rc3
Requires-Dist: nonebot-adapter-onebot >=2.0.0b1
